{
    "trending": [
        {
            "name": "Creed II",
            "poster": "https://m.media-amazon.com/images/M/MV5BMTcxMjUwNjQ5N15BMl5BanBnXkFtZTgwNjk4MzI4NjM@._V1_QL50.jpg",
            "id": "tt6343314"
        },
        {
            "name": "Fantastic Beasts: The Crimes of Grindelwald",
            "poster": "https://m.media-amazon.com/images/M/MV5BZjFiMGUzMTAtNDAwMC00ZjRhLTk0OTUtMmJiMzM5ZmVjODQxXkEyXkFqcGdeQXVyMDM2NDM2MQ@@._V1_QL50.jpg",
            "id": "tt4123430"
        },
        {
            "name": "Bohemian Rhapsody",
            "poster": "https://m.media-amazon.com/images/M/MV5BNDg2NjIxMDUyNF5BMl5BanBnXkFtZTgwMzEzNTE1NTM@._V1_QL50.jpg",
            "id": "tt1727824"
        },
        {
            "name": "The Ballad of Buster Scruggs",
            "poster": "https://m.media-amazon.com/images/M/MV5BYjRkYTI3M2EtZWQ4Ny00OTA2LWFmMTMtY2E4MTEyZmNjOTMxXkEyXkFqcGdeQXVyNDg4NjY5OTQ@._V1_QL50.jpg",
            "id": "tt6412452"
        },
        {
            "name": "Ralph Breaks the Internet",
            "poster": "https://m.media-amazon.com/images/M/MV5BMTYyNzEyNDAzOV5BMl5BanBnXkFtZTgwNTk3NDczNjM@._V1_QL50.jpg",
            "id": "tt5848272"
        },
        {
            "name": "Venom",
            "poster": "https://m.media-amazon.com/images/M/MV5BNzAwNzUzNjY4MV5BMl5BanBnXkFtZTgwMTQ5MzM0NjM@._V1_QL50.jpg",
            "id": "tt1270797"
        },
        {
            "name": "The Lion King",
            "poster": "https://m.media-amazon.com/images/M/MV5BMTg5NTY3OTU2N15BMl5BanBnXkFtZTgwOTgyOTA4NjM@._V1_QL50.jpg",
            "id": "tt6105098"
        }
    ]
}